mgba/__init__.py
mgba/_pylib.abi3.so
mgba/arm.py
mgba/audio.py
mgba/core.py
mgba/debugger.py
mgba/gamedata.py
mgba/gb.py
mgba/gba.py
mgba/image.py
mgba/log.py
mgba/memory.py
mgba/png.py
mgba/sm83.py
mgba/thread.py
mgba/tile.py
mgba/vfs.py
mgba-0.10.2.dist-info/LICENSE
mgba-0.10.2.dist-info/METADATA
mgba-0.10.2.dist-info/WHEEL
mgba-0.10.2.dist-info/top_level.txt
mgba-0.10.2.dist-info/RECORD
