Metadata-Version: 2.1
Name: mgba
Version: 0.10.2
Summary: Wheels for the Python bindings of mGBA
License-File: LICENSE
Requires-Dist: cffi >=1.6
Requires-Dist: cached-property
Provides-Extra: pil
Requires-Dist: Pillow >=2.3 ; extra == 'pil'
